surfacedist/__init__.py
surfacedist/lookup_tables.py
surfacedist/metrics.py
surfacedist-0.1.0.dist-info/LICENSE
surfacedist-0.1.0.dist-info/WHEEL
surfacedist-0.1.0.dist-info/METADATA
surfacedist-0.1.0.dist-info/RECORD
