Metadata-Version: 2.1
Name: surfacedist
Version: 0.1.0
Summary: 
License: Apache-2.0
Author: Simon Biggs
Author-email: simon.biggs@radiotherapy.ai
Requires-Python: >=3.7,<4.0
Classifier: License :: OSI Approved :: Apache Software License
Classifier: Programming Language :: Python :: 3
Classifier: Programming Language :: Python :: 3.7
Classifier: Programming Language :: Python :: 3.8
Classifier: Programming Language :: Python :: 3.9
Requires-Dist: absl-py
Requires-Dist: numpy
Requires-Dist: scipy
